{
  "$schema": "http://json-schema.org/draft-04/schema#",
  "type": "object",
  "id": "http://org.vpk.rmt/common/datamodel/model/Station",
  "javaType": "org.vpk.rmt.common.datamodel.model.Station",
  "extends": {
    "$ref": "DatamodelObject.json"
  },
  "properties": {
    "id": {
      "required": false,
      "type": "string"
    },
    "externalId": {
      "required": true,
      "type": "array",
      "minItems": 1,
      "uniqueItems": true,
      "items": {
        "$ref": "ExternalId.json"
      }
    },
    "type": {
      "required": true,
      "type": "string"
    },
    "duration": {
      "required": false,
      "type": "string"
    }
  }
}
